mkw_ropcop/__init__.py
mkw_ropcop/_dock_widget.py
mkw_ropcop/_version.py
mkw_ropcop/napari.yaml
mkw_ropcop/ropcop_browser_gui.py
mkw_ropcop/ropcop_segmenter_widget.py
mkw_ropcop-0.1.0.dist-info/METADATA
mkw_ropcop-0.1.0.dist-info/WHEEL
mkw_ropcop-0.1.0.dist-info/entry_points.txt
mkw_ropcop-0.1.0.dist-info/top_level.txt
mkw_ropcop-0.1.0.dist-info/RECORD
